pteste.py
setup.py
plimoTeste.egg-info/PKG-INFO
plimoTeste.egg-info/SOURCES.txt
plimoTeste.egg-info/dependency_links.txt
plimoTeste.egg-info/requires.txt
plimoTeste.egg-info/top_level.txt