Metadata-Version: 1.1
Name: plimoTeste
Version: 0.1
Summary: Um projeto estupido usando dependencias
Home-page: https://github.com/plimo263
Author: Marcos Felipe da Silva Jardim
Author-email: plimo263@gmail.com
License: MIT
Platform: UNKNOWN
Classifier: Programming Language :: Python :: 3
Classifier: Programming Language :: Python :: 3.2
Classifier: Programming Language :: Python :: 3.3
Classifier: Programming Language :: Python :: 3.4
Classifier: Programming Language :: Python :: 3.5
Classifier: Programming Language :: Python :: 3.6
